papierstat/__init__.py
papierstat/datasets/__init__.py
papierstat/datasets/carreau.py
papierstat/datasets/cat.py
papierstat/datasets/data_helper.py
papierstat/datasets/documentation.py
papierstat/datasets/dummies.py
papierstat/datasets/duration.py
papierstat/datasets/enedis.py
papierstat/datasets/geojson.py
papierstat/datasets/graph.py
papierstat/datasets/movies.py
papierstat/datasets/search.py
papierstat/datasets/sentiment.py
papierstat/datasets/titanic.py
papierstat/datasets/tweets.py
papierstat/datasets/wines.py
papierstat/datasets/data/__init__.py
papierstat/datasets/data/adult.data.gz
papierstat/datasets/data/adult.test.gz
papierstat/datasets/data/countries.geo.json
papierstat/datasets/data/reunion.zip
papierstat/datasets/data/reunion_rect.zip
papierstat/datasets/data/search_tiny_test.txt
papierstat/datasets/data/search_tiny_train.txt
papierstat/datasets/data/titanic.txt
papierstat/datasets/data/titanic3.csv
papierstat/datasets/data/tweets_macron_sijetaispresident_201609.zip
papierstat/datasets/data/wine.data.txt
papierstat/datasets/data/wines-quality.csv
papierstat/mltricks/__init__.py
papierstat/mltricks/sklearn_base_learner_category.py
papierstat/mltricks/sklearn_example_classifier.py
papierstat/mltricks/text_vectorizer_transformer.py
papierstat-0.2.408.dist-info/LICENSE.txt
papierstat-0.2.408.dist-info/METADATA
papierstat-0.2.408.dist-info/WHEEL
papierstat-0.2.408.dist-info/top_level.txt
papierstat-0.2.408.dist-info/RECORD
