Metadata-Version: 2.1
Name: papierstat
Version: 0.2.408
Summary: Helpers for teaching materials about machine learning.
Home-page: http://www.xavierdupre.fr/app/papierstat/helpsphinx/index.html
Author: Xavier Dupré
Author-email: xavier.dupre@gmail.com
License: MIT
Download-URL: https://github.com/sdpython/papierstat/
Keywords: papierstat,Xavier Dupré
Platform: UNKNOWN
Classifier: Programming Language :: Python :: 3
Classifier: Intended Audience :: Developers
Classifier: Topic :: Scientific/Engineering
Classifier: Topic :: Education
Classifier: License :: OSI Approved :: MIT License
Classifier: Development Status :: 5 - Production/Stable
Requires-Dist: scikit-learn (>=0.21.0)
Requires-Dist: pandas
Requires-Dist: mlinsights
Requires-Dist: matplotlib
Requires-Dist: pandas-streaming
Provides-Extra: datasets.carreau
Requires-Dist: dbfread ; extra == 'datasets.carreau'
Requires-Dist: geopandas ; extra == 'datasets.carreau'
Requires-Dist: fiona ; extra == 'datasets.carreau'
